entropyrank/EntropyRank.py
entropyrank/__init__.py
entropyrank/requirements.txt
entropyrank/word_statistics.json
entropyrank/stopwords/FoxStopList.txt
entropyrank/stopwords/SmartStopList.txt
entropyrank/stopwords/TerrierStopList.txt
entropyrank-1.0.3.dist-info/METADATA
entropyrank-1.0.3.dist-info/WHEEL
entropyrank-1.0.3.dist-info/licenses/LICENSE
entropyrank-1.0.3.dist-info/RECORD
