Metadata-Version: 2.1
Name: entropyrank
Version: 1.0.3
Summary: Entropy Rank keyphrase extractor
Project-URL: Homepage, https://github.com/tsalex1992/EntropyRank
Project-URL: Bug Tracker, https://github.com/tsalex1992/EntropyRank/issues
Author-email: Alexander Tsvetkov <tsalex1992@gmail.com>
License: Apache-2.0
License-File: LICENSE
Keywords: EntropyRank,entropy,keyphrase extraction,keywords extraction
Classifier: Operating System :: OS Independent
Classifier: Programming Language :: Python :: 3
Requires-Python: >=3.10
Requires-Dist: keyphrase-vectorizers==0.0.11
Requires-Dist: numpy>=1.24.0
Requires-Dist: spacy>=3.6.0
Requires-Dist: torch==2.0.1
Requires-Dist: torchaudio==2.0.2
Requires-Dist: torchvision==0.15.2
Requires-Dist: transformers==4.30.0
